{
  "updated_at": "2026-04-23 18:54:44 UTC",
  "prices": {
    "BTC": {
      "price": 77829.4,
      "change": -1.51
    },
    "ETH": {
      "price": 2309.97,
      "change": -3.73
    },
    "SOL": {
      "price": 85.432,
      "change": -3.17
    },
    "BNB": {
      "price": 634.92,
      "change": -1.7
    },
    "TAO": {
      "price": 242.81,
      "change": -1.79
    },
    "NEAR": {
      "price": 1.3913,
      "change": -1.97
    }
  },
  "bots": {
    "multi": {
      "name": "Multi Crypto",
      "exchange": "Bitget",
      "balance": 679.32,
      "equity": 678.58,
      "positions": [
        {
          "symbol": "SOL",
          "side": "short",
          "size": 0.7,
          "entry": 84.894,
          "pnl": -0.38,
          "pnl_pct": 0.0
        },
        {
          "symbol": "ETH",
          "side": "short",
          "size": 0.02,
          "entry": 2310.73,
          "pnl": 0.02,
          "pnl_pct": 0.0
        },
        {
          "symbol": "BTC",
          "side": "long",
          "size": 0.0008,
          "entry": 78299.4,
          "pnl": -0.38,
          "pnl_pct": 0.0
        }
      ],
      "pairs": [
        "BTC",
        "ETH",
        "SOL",
        "BNB",
        "TAO"
      ],
      "leverage": 10,
      "risk_pct": 8
    },
    "near": {
      "name": "NEAR Accumulator",
      "exchange": "Bitmart",
      "usdt": 255.13,
      "near_held": 892.4865,
      "leverage": 5,
      "sl_pct": 2.5,
      "tp_pct": 6.0
    },
    "poly": {
      "name": "Polymarket AI",
      "exchange": "Polygon",
      "balance": 139.23,
      "positions": [
        {
          "question": "Gwangju: Mark Lajal vs Maximus Jones",
          "action": "BUY_YES",
          "buy_price": 0.61,
          "current_price": 0.999,
          "pnl_pct": 63.8,
          "bet_usdt": 5.49,
          "days_left": 6,
          "yes_prob": 0.999
        },
        {
          "question": "US x Iran permanent peace deal by May 31, 2026?",
          "action": "BUY_NO",
          "buy_price": 0.37,
          "current_price": 0.67,
          "pnl_pct": 81.1,
          "bet_usdt": 8.31,
          "days_left": 37,
          "yes_prob": 0.33
        }
      ],
      "min_edge": 20
    },
    "mt5": {
      "name": "Forex MT5",
      "exchange": "Bitget TFI",
      "balance": 1092,
      "symbols": [
        "EURUSD",
        "USDJPY",
        "USDCHF",
        "US500"
      ],
      "leverage": 100,
      "risk_pct": 1
    }
  },
  "stats": {
    "total_bots": 4,
    "near_held": 892.4865,
    "poly_balance": 139.23,
    "multi_equity": 678.58
  }
}