{
  "last_update": "2026-06-29T11:24:41.657942+00:00",
  "market": {
    "fear_greed": 12,
    "symbols": {
      "BTC/USDT": {
        "change_24h_pct": -0.7,
        "change_7d_pct": -6.42,
        "regime": "neutral"
      },
      "ETH/USDT": {
        "change_24h_pct": -0.7,
        "change_7d_pct": -9.06,
        "regime": "neutral"
      }
    }
  },
  "spot_portfolio": {
    "equity_usdt": 16667.83,
    "usdt_free": 12227.19,
    "usdt_total": 12227.19,
    "positions": {
      "BTC/USDT": {
        "amount": 0.050971,
        "avg_price": 63972.94,
        "invested_usdt": 3260.76,
        "realized_pnl_usdt": 0.0,
        "last_tp_price": 0.0,
        "in_cooldown": false
      },
      "ETH/USDT": {
        "amount": 0.93069953,
        "avg_price": 1682.99,
        "invested_usdt": 1566.36,
        "realized_pnl_usdt": 0.0,
        "last_tp_price": 0.0,
        "in_cooldown": false
      }
    }
  }
}