{
  "last_update": "2026-06-30T03:24:45.009083+00:00",
  "market": {
    "fear_greed": 15,
    "symbols": {
      "BTC/USDT": {
        "change_24h_pct": -0.3,
        "change_7d_pct": -4.56,
        "regime": "neutral"
      },
      "ETH/USDT": {
        "change_24h_pct": 0.45,
        "change_7d_pct": -4.5,
        "regime": "neutral"
      }
    }
  },
  "spot_portfolio": {
    "equity_usdt": 16683.29,
    "usdt_free": 12075.36,
    "usdt_total": 12075.36,
    "positions": {
      "BTC/USDT": {
        "amount": 0.052713,
        "avg_price": 63845.98,
        "invested_usdt": 3365.51,
        "realized_pnl_usdt": 0.0,
        "last_tp_price": 0.0,
        "in_cooldown": false
      },
      "ETH/USDT": {
        "amount": 0.95849953,
        "avg_price": 1680.83,
        "invested_usdt": 1611.07,
        "realized_pnl_usdt": 0.0,
        "last_tp_price": 0.0,
        "in_cooldown": false
      }
    }
  }
}